{
    "count": 2,
    "entries": [
        {
            "id": 1,
            "model": "Default SpaCy NER, Tok2Vec",
            "f1-score": "10.72",
            "standard-error": "1.549",
            "lb-ci": "7.571",
            "ub-ci": "13.56"
        },
        {
            "id": 2,
            "model": "Default SpaCy NER + 2022 Entity Ruler, Tok2Vec",
            "f1-score": "11.92",
            "standard-error": "2.034",
            "lb-ci": "8.025",
            "ub-ci": "16.78"
        }
    ]
}